bouto
